popcon/__init__.py
popcon/datasets/__init__.py
popcon/datasets/io.py
popcon/datasets/data/duke/atlas.csv
popcon/datasets/data/duke/blocks.csv
popcon/datasets/data/duke/participants.csv
popcon/datasets/data/duke/graphs/sub-54776_ses-1_dti.ssv
popcon/datasets/data/duke/graphs/sub-54777_ses-1_dti.ssv
popcon/datasets/data/duke/graphs/sub-54779_ses-1_dti.ssv
popcon/datasets/data/duke/graphs/sub-54781_ses-1_dti.ssv
popcon/datasets/data/duke/graphs/sub-54790_ses-1_dti.ssv
popcon/datasets/data/duke/graphs/sub-54793_ses-1_dti.ssv
popcon/datasets/data/duke/graphs/sub-54794_ses-1_dti.ssv
popcon/datasets/data/duke/graphs/sub-54797_ses-1_dti.ssv
popcon/datasets/data/duke/graphs/sub-54811_ses-1_dti.ssv
popcon/datasets/data/duke/graphs/sub-54813_ses-1_dti.ssv
popcon/datasets/data/duke/graphs/sub-54815_ses-1_dti.ssv
popcon/datasets/data/duke/graphs/sub-54817_ses-1_dti.ssv
popcon/datasets/data/duke/graphs/sub-54821_ses-1_dti.ssv
popcon/datasets/data/duke/graphs/sub-54823_ses-1_dti.ssv
popcon/datasets/data/duke/graphs/sub-54829_ses-1_dti.ssv
popcon/datasets/data/duke/graphs/sub-54831_ses-1_dti.ssv
popcon/datasets/data/duke/graphs/sub-54833_ses-1_dti.ssv
popcon/datasets/data/duke/graphs/sub-54835_ses-1_dti.ssv
popcon/datasets/data/duke/graphs/sub-54842_ses-1_dti.ssv
popcon/datasets/data/duke/graphs/sub-54847_ses-1_dti.ssv
popcon/datasets/data/duke/graphs/sub-54849_ses-1_dti.ssv
popcon/datasets/data/duke/graphs/sub-54851_ses-1_dti.ssv
popcon/datasets/data/duke/graphs/sub-54853_ses-1_dti.ssv
popcon/datasets/data/duke/graphs/sub-54855_ses-1_dti.ssv
popcon/datasets/data/duke/graphs/sub-54864_ses-1_dti.ssv
popcon/datasets/data/duke/graphs/sub-54866_ses-1_dti.ssv
popcon/datasets/data/duke/graphs/sub-54868_ses-1_dti.ssv
popcon/datasets/data/duke/graphs/sub-54870_ses-1_dti.ssv
popcon/datasets/data/duke/graphs/sub-54883_ses-1_dti.ssv
popcon/datasets/data/duke/graphs/sub-54885_ses-1_dti.ssv
popcon/datasets/data/duke/graphs/sub-54887_ses-1_dti.ssv
popcon-0.0.8.dist-info/LICENSE
popcon-0.0.8.dist-info/METADATA
popcon-0.0.8.dist-info/WHEEL
popcon-0.0.8.dist-info/top_level.txt
popcon-0.0.8.dist-info/RECORD
