Metadata-Version: 2.1
Name: popcon
Version: 0.0.8
Summary: Population-level connectome analysis in Python!
Home-page: https://github.com/v715/popcon
Author: ('Vivek Gopalakrishnan',)
Author-email: vgopala4@jhu.edu
License: MIT
Platform: UNKNOWN
Classifier: Development Status :: 3 - Alpha
Classifier: Intended Audience :: Science/Research
Classifier: Topic :: Scientific/Engineering :: Mathematics
Classifier: License :: OSI Approved :: Apache Software License
Classifier: Programming Language :: Python :: 3
Classifier: Programming Language :: Python :: 3.5
Classifier: Programming Language :: Python :: 3.6
Classifier: Programming Language :: Python :: 3.7
Requires-Dist: graspy (>=0.1)
Requires-Dist: mgc (>=0.0.1)
Requires-Dist: numpy (>=1.18)
Requires-Dist: pandas (>=0.25.0)
Requires-Dist: statsmodels (>=0.10.0)
Requires-Dist: tqdm (>=4.41.0)
